defermi_gui/__init__.py
defermi_gui/binding_energies.py
defermi_gui/brouwer.py
defermi_gui/chempots.py
defermi_gui/ctls.py
defermi_gui/data.py
defermi_gui/defaults.py
defermi_gui/doping.py
defermi_gui/dos.py
defermi_gui/fermi_level.py
defermi_gui/formation_energies.py
defermi_gui/home.py
defermi_gui/info.py
defermi_gui/initialize.py
defermi_gui/inputs.py
defermi_gui/main.py
defermi_gui/overview.py
defermi_gui/thermodynamics.py
defermi_gui/utils.py
defermi_gui/.streamlit/config.toml
defermi_gui/cli/__init__.py
defermi_gui/cli/main.py
defermi_gui/presets/complex.csv
defermi_gui/presets/complex.defermi
defermi_gui/presets/silicon.csv
defermi_gui/presets/silicon.defermi
defermi_gui/presets/test.defermi
defermi_gui/presets/vacancies.csv
defermi_gui/presets/vacancies.defermi
defermi_gui/presets/vacancies_interstitials.csv
defermi_gui/presets/vacancies_interstitials.defermi
defermi_gui/presets/vacancies_substitutions.csv
defermi_gui/presets/vacancies_substitutions.defermi
defermi_gui-0.1.0.dist-info/METADATA
defermi_gui-0.1.0.dist-info/WHEEL
defermi_gui-0.1.0.dist-info/entry_points.txt
defermi_gui-0.1.0.dist-info/top_level.txt
defermi_gui-0.1.0.dist-info/RECORD
