Metadata-Version: 2.4
Name: defermi-gui
Version: 0.1.0
Summary: User interface for defermi
Author: Lorenzo Villa
Requires-Python: >=3.11
Requires-Dist: defermi
Requires-Dist: streamlit>=1.51.0
Requires-Dist: seaborn
Provides-Extra: test
Requires-Dist: pytest; extra == "test"
